{"open_count": 0, "closed_count": 5, "blocked_count": 96, "wins": 2, "losses": 3, "win_rate_pct": 40.0, "avg_pnl_pct": 0.3586, "last_closed": {"opened_timestamp": 1775473721, "symbol": "XRP-USD", "action": "SELL", "entry_price": 1.34771, "confidence": 25.0, "strategy": "B_ONLY", "winning_strategy": "B_VOL_BREAKOUT", "preferred_strategy": "B_VOL_BREAKOUT", "regime": "RANGE", "trend": "Bearish", "rsi": 100.0, "status": "CLOSED", "source": "signal_history", "exit_timestamp": 1775492301, "exit_price": 1.35046, "pnl_pct": -0.204, "outcome": "LOSS"}}